pyBigKinds/__init__.py
pyBigKinds/_version.py
pyBigKinds/base.py
pyBigKinds/preprocessing.py
pyBigKinds/representation.py
pyBigKinds/visualization.py
pyBigKinds-1.2.9.dist-info/LICENSE
pyBigKinds-1.2.9.dist-info/METADATA
pyBigKinds-1.2.9.dist-info/WHEEL
pyBigKinds-1.2.9.dist-info/top_level.txt
pyBigKinds-1.2.9.dist-info/RECORD
