Metadata-Version: 2.1
Name: pyBigKinds
Version: 1.2.9
Summary: BigKinds Data Analysis Toolkit for python
Home-page: https://github.com/sorrychoe/pyBigKinds
Author: Sorrychoe
License: MIT
Project-URL: Source Code, https://github.com/sorrychoe/pyBigKinds
Project-URL: Bug Tracker, https://github.com/sorrychoe/pyBigKinds/issues
Keywords: Journalism,Preprocessing-data,Text-mining,BigKinds
Requires-Python: >=3.8
License-File: LICENSE
Requires-Dist: matplotlib>=3.5.3
Requires-Dist: pandas>=2
Requires-Dist: wordcloud>=1.8.2.2
Requires-Dist: scikit-learn>=1.0.0
Requires-Dist: tomotopy>=0.12.4
Requires-Dist: openpyxl>=3.1.2
Requires-Dist: mlxtend>=0.22.0
Provides-Extra: dev
Requires-Dist: flake8>=3.9; extra == "dev"
Requires-Dist: isort>=5.7; extra == "dev"
Requires-Dist: pre-commit>=3; extra == "dev"
Requires-Dist: pylint>=2.9; extra == "dev"
Requires-Dist: pytest>=7; extra == "dev"
